Workbook
Name invest_mes: Planilha2!$C$16
Name patrimonio: Planilha2!$C$19
Name rendimento_carteira: Planilha2!$C$12
Name tempo_anos: Planilha2!$C$17
Name tx_red_mensal: Planilha2!$C$18

Sheet Planilha2
B10: CONFIGURAÇÕES
B11: Salário | C11: 5000
B12: Rendimento Carteira | C12: 0.01
B13: Sugestão de Investimento 30% | C13: =C11*30% -> 1500
B15: INVESTIMENTO MENSAL
B16: Quanto investir por mês | C16: 1500
B17: Por quantos anos? | C17: 5
B18: Taxa de rendimento mensal? | C18: 0.01079
B19: Total de Patrimonio | C19: =FV(tx_red_mensal,tempo_anos*12,invest_mes*-1) -> 125665.37
B20: Dividendos mensais | C20: =patrimonio*rendimento_carteira -> 1256.6537
B22: CENÁRIOS | D22: Dividendos
A23: 2 | B23: Quanto em 2 anos? | C23: =FV($C$18,$A23*12,$C$16*-1) -> 40841.441 | D23: =C23*rendimento_carteira -> 408.41441
A24: 5 | B24: Quanto em 5 anos? | C24: =FV($C$18,$A24*12,$C$16*-1) -> 125665.37 | D24: =C24*rendimento_carteira -> 1256.6537
A25: 10 | B25: Quanto em 10 anos? | C25: =FV($C$18,$A25*12,$C$16*-1) -> 364926.32 | D25: =C25*rendimento_carteira -> 3649.2632
A26: 20 | B26: Quanto em 20 anos? | C26: =FV($C$18,$A26*12,$C$16*-1) -> 1687797.6 | D26: =C26*rendimento_carteira -> 16877.976
A27: 30 | B27: Quanto em 30 anos? | C27: =FV($C$18,$A27*12,$C$16*-1) -> 6483254.5 | D27: =C27*rendimento_carteira -> 64832.545
B30: Tipo de Perfil | E30: Moderado
B31: Valor a ser investido por mês | E31: 1500
B33: TIPO DE FII | C33: Percentual Sugerido | E33: Valores
B34: PAPEL | C34: =VLOOKUP(($E$30&"-"&B34),Planilha1!$A:$D,4,FALSE) -> 0.32 | E34: =C34*$E$31 -> 480
B35: TIJOLO | C35: =VLOOKUP(($E$30&"-"&B35),Planilha1!$A:$D,4,FALSE) -> 0.4 | E35: =C35*$E$31 -> 600
B36: HÍBRIDOS | C36: =VLOOKUP(($E$30&"-"&B36),Planilha1!$A:$D,4,FALSE) -> 0.08 | E36: =C36*$E$31 -> 120
B37: FOFs | C37: =VLOOKUP(($E$30&"-"&B37),Planilha1!$A:$D,4,FALSE) -> 0.1 | E37: =C37*$E$31 -> 150
B38: DESENVOLVIMENTO | C38: =VLOOKUP(($E$30&"-"&B38),Planilha1!$A:$D,4,FALSE) -> 0.05 | E38: =C38*$E$31 -> 75
B39: HOTELARIAS | C39: =VLOOKUP(($E$30&"-"&B39),Planilha1!$A:$D,4,FALSE) -> 0.05 | E39: =C39*$E$31 -> 75
E40: =SUM(E34:E39) -> 1500

Sheet Planilha1
A1: CHAVE | B1: PERFIL | C1: TIPO DE FII | D1: %
A2: =B2&"-"&C2 -> Conservador-PAPEL | B2: Conservador | C2: PAPEL | D2: 0.3
A3: =B3&"-"&C3 -> Conservador-TIJOLO | B3: Conservador | C3: TIJOLO | D3: 0.5
A4: =B4&"-"&C4 -> Conservador-HÍBRIDOS | B4: Conservador | C4: HÍBRIDOS | D4: 0.1
A5: =B5&"-"&C5 -> Conservador-FOFs | B5: Conservador | C5: FOFs | D5: 0.1
A6: =B6&"-"&C6 -> Conservador-DESENVOLVIMENTO | B6: Conservador | C6: DESENVOLVIMENTO | D6: 0
A7: =B7&"-"&C7 -> Conservador-HOTELARIAS | B7: Conservador | C7: HOTELARIAS | D7: 0
A8: =B8&"-"&C8 -> Moderado-PAPEL | B8: Moderado | C8: PAPEL | D8: 0.32
A9: =B9&"-"&C9 -> Moderado-TIJOLO | B9: Moderado | C9: TIJOLO | D9: 0.4
A10: =B10&"-"&C10 -> Moderado-HÍBRIDOS | B10: Moderado | C10: HÍBRIDOS | D10: 0.08
A11: =B11&"-"&C11 -> Moderado-FOFs | B11: Moderado | C11: FOFs | D11: 0.1
A12: =B12&"-"&C12 -> Moderado-DESENVOLVIMENTO | B12: Moderado | C12: DESENVOLVIMENTO | D12: 0.05
A13: =B13&"-"&C13 -> Moderado-HOTELARIAS | B13: Moderado | C13: HOTELARIAS | D13: 0.05
... A19: =B19&"-"&C19 -> Agressivo-HOTELARIAS | B19: Agressivo | C19: HOTELARIAS | D19: 0.1
